{"type":"PR","pr":{"number":118,"head":"31a7d98c2a469276bb981c61fa8c18aeae3acaf9"},"user":"Ad Spiers","status":"draft","branch":"cms/demos","collection":"presenting","title":"Hands-On Demonstrations","description":"Haptics Symposium strongly encourages demonstrations of all kinds - for example, of novel developments in haptics-related devices, software or experiments that are of interest to the conference audience.\n\nSubmission of hands-on demonstrations is open to all members of the haptics research community. Authors of accepted papers are particularly welcome to apply for demonstration space to support their presentation. Demonstrations must be free of commercial content; companies wishing to showcase products should apply for exhibitor status.","objects":{"entry":{"path":"site/content/presenting/demos.md","sha":"e468f50e80d61556c8d5c2930eb540539d4f19d4"},"files":[]},"timeStamp":"2019-12-19T12:56:25.976Z"}